{
  "status": "200",
  "success": true,
  "message": "Data fetched successfully",
  "total": 10,
  "updatedAt": "28/04/2026, 10:45:01 PM",
  "data": [
    {
      "id": "1540066415",
      "name": "PBKS vs RR",
      "tounament": "Watch the live stream of TATA IPL 2026 match between Punjab Kings and Rajasthan Royals",
      "Portrait_Image": "https://img.hotstar.com/image/upload/f_auto/sources/r1/cms/prod/2250/1777289632250-h",
      "Landscape_Image": "https://img.hotstar.com/image/upload/f_auto,t_hcdl/sources/r1/cms/prod/2250/1777289632250-h",
      "provider": "Hotstar",
      "language": [
        "English",
        "Hindi",
        "Tamil",
        "Bengali",
        "Malayalam",
        "Punjabi",
        "Marathi",
        "Haryanvi",
        "Bhojpuri",
        "Telugu",
        "Kannada",
        "Gujarati"
      ],
      "isLive": true,
      "metaDetailVerbiage": "12 Languages • Sports",
      "genre": "Sports"
    },
    {
      "id": "142302",
      "name": "ATP Masters Mutua Madrid Open 2026",
      "tounament": "ATP Masters Mutua Madrid Open 2026",
      "Portrait_Image": "https://images.fancode.com/aig/match/v1777356001262/142302_CASACARDS_PARTNER_2_3_700_1050.png",
      "Landscape_Image": "https://images.fancode.com/aig/match/v1777356001262/142302_CASACARDS_PARTNER_16_9_1920_1080.png",
      "provider": "FanCode",
      "language": [
        "English"
      ],
      "isLive": true,
      "metaDetailVerbiage": "English • Lawn-tennis • U",
      "genre": "Lawn-tennis"
    },
    {
      "id": "141954",
      "name": "West Indies Championship 2026",
      "tounament": "West Indies Championship 2026",
      "Portrait_Image": "https://images.fancode.com/aig/match/v1776614400554/141954_CASACARDS_PARTNER_2_3_700_1050.png",
      "Landscape_Image": "https://images.fancode.com/aig/match/v1776614400554/141954_CASACARDS_PARTNER_16_9_1920_1080.png",
      "provider": "FanCode",
      "language": [
        "English"
      ],
      "isLive": true,
      "metaDetailVerbiage": "English • Cricket • U",
      "genre": "Cricket"
    },
    {
      "id": "1540068500",
      "name": "Chinese Taipei vs Indonesia: Uber Cup, Group Stage",
      "tounament": "Watch the live stream of the group stage match between Indonesia and France from BWF Thomas Cup Finals",
      "Portrait_Image": "https://img.hotstar.com/image/upload/f_auto/sources/r1/cms/prod/5084/1777384785084-h",
      "Landscape_Image": "https://img.hotstar.com/image/upload/f_auto,t_hcdl/sources/r1/cms/prod/5084/1777384785084-h",
      "provider": "Hotstar",
      "language": [
        "English"
      ],
      "isLive": true,
      "metaDetailVerbiage": "English • Sports",
      "genre": "Sports"
    },
    {
      "id": "141955",
      "name": "Windward Islands Volcanoes VS Guyana Harpy Eagles",
      "tounament": "West Indies Championship 2026",
      "Portrait_Image": "https://images.fancode.com/aig/match/v1776614400470/141955_CASACARDS_PARTNER_2_3_700_1050.png",
      "Landscape_Image": "https://images.fancode.com/aig/match/v1776614400470/141955_CASACARDS_PARTNER_16_9_1920_1080.png",
      "provider": "FanCode",
      "language": [
        "English"
      ],
      "isLive": true,
      "metaDetailVerbiage": "English • Cricket • U",
      "genre": "Cricket"
    },
    {
      "id": "142324",
      "name": "ATP Masters Mutua Madrid Open 2026",
      "tounament": "ATP Masters Mutua Madrid Open 2026",
      "Portrait_Image": "https://images.fancode.com/aig/match/v1777363200775/142324_CASACARDS_PARTNER_2_3_700_1050.png",
      "Landscape_Image": "https://images.fancode.com/aig/match/v1777363200775/142324_CASACARDS_PARTNER_16_9_1920_1080.png",
      "provider": "FanCode",
      "language": [
        "English"
      ],
      "isLive": true,
      "metaDetailVerbiage": "English • Lawn-tennis • U",
      "genre": "Lawn-tennis"
    },
    {
      "id": "141953",
      "name": "Leeward Islands Hurricanes VS Trinidad & Tobago Red Force",
      "tounament": "West Indies Championship 2026",
      "Portrait_Image": "https://images.fancode.com/aig/match/v1776614400512/141953_CASACARDS_PARTNER_2_3_700_1050.png",
      "Landscape_Image": "https://images.fancode.com/aig/match/v1776614400512/141953_CASACARDS_PARTNER_16_9_1920_1080.png",
      "provider": "FanCode",
      "language": [
        "English"
      ],
      "isLive": true,
      "metaDetailVerbiage": "English • Cricket • U",
      "genre": "Cricket"
    },
    {
      "id": "141864",
      "name": "ATP Masters Mutua Madrid Open 2026",
      "tounament": "ATP Masters Mutua Madrid Open 2026",
      "Portrait_Image": "https://www.fancode.com/skillup-uploads/cms-media/141864_6034_ATP_LOC_PARTNER_2x3.jpg",
      "Landscape_Image": "https://www.fancode.com/skillup-uploads/cms-media/141864_6034_ATP_LOC_PARTNER_16x9.jpg",
      "provider": "FanCode",
      "language": [
        "English"
      ],
      "isLive": true,
      "metaDetailVerbiage": "English • Lawn-tennis • U",
      "genre": "Lawn-tennis"
    },
    {
      "id": "1540068503",
      "name": "Korea vs Thailand: Uber Cup, Group Stage",
      "tounament": "Watch the live stream of the group stage match between Korea and Thailand from BWF Uber Cup Finals",
      "Portrait_Image": "https://img.hotstar.com/image/upload/f_auto/sources/r1/cms/prod/174/1777376520174-h",
      "Landscape_Image": "https://img.hotstar.com/image/upload/f_auto,t_hcdl/sources/r1/cms/prod/174/1777376520174-h",
      "provider": "Hotstar",
      "language": [
        "English"
      ],
      "isLive": true,
      "metaDetailVerbiage": "English • Sports",
      "genre": "Sports"
    },
    {
      "id": "141865",
      "name": "ATP Masters Mutua Madrid Open 2026",
      "tounament": "ATP Masters Mutua Madrid Open 2026",
      "Portrait_Image": "https://www.fancode.com/skillup-uploads/cms-media/141865_6034_ATP_LOC_PARTNER_2x3.jpg",
      "Landscape_Image": "https://www.fancode.com/skillup-uploads/cms-media/141865_6034_ATP_LOC_PARTNER_16x9.jpg",
      "provider": "FanCode",
      "language": [
        "English"
      ],
      "isLive": true,
      "metaDetailVerbiage": "English • Lawn-tennis • U",
      "genre": "Lawn-tennis"
    }
  ]
}
