{
  "success": true,
  "message": "Live matches fetched successfully",
  "total": 6,
  "updatedAt": "10/10/2025, 08:52:27 PM",
  "data": [
    {
      "id": "1540051854",
      "name": "New Zealand W vs Bangladesh W",
      "tounament": "Watch the live stream of ICC Women’s Cricket World Cup 2025 match between New Zealand Women and Bangladesh Women",
      "Portrait_Image": "https://img.hotstar.com/image/upload/f_auto/sources/r1/cms/prod/8196/1760037258196-h",
      "Landscape_Image": "https://img.hotstar.com/image/upload/f_auto,t_hcdl/sources/r1/cms/prod/8196/1760037258196-h",
      "provider": "Hotstar",
      "language": [
        "English"
      ],
      "isLive": true,
      "metaDetailVerbiage": "English • Sports",
      "genre": "Sports"
    },
    {
      "id": "1540050534",
      "name": "Gujarat Giants vs Dabang Delhi K.C.",
      "tounament": "Watch the live stream of the Pro Kabaddi League 2025 match between Gujarat Giants and Dabang Delhi K.C.",
      "Portrait_Image": "https://img.hotstar.com/image/upload/f_auto/sources/r1/cms/prod/1351/1760008151351-h",
      "Landscape_Image": "https://img.hotstar.com/image/upload/f_auto,t_hcdl/sources/r1/cms/prod/1351/1760008151351-h",
      "provider": "Hotstar",
      "language": [
        "English",
        "Hindi",
        "Tamil",
        "Marathi",
        "Haryanvi",
        "Bhojpuri",
        "Telugu",
        "Kannada"
      ],
      "isLive": true,
      "metaDetailVerbiage": "8 Languages • Sports",
      "genre": "Sports"
    },
    {
      "id": "137182",
      "name": "Oman VS Papua New Guinea",
      "tounament": "ICC Menâs T20 World Cup Asia & EAP Qualifier, 2025",
      "Portrait_Image": "https://images.fancode.com/aig/match/v1/137182_CASACARDS_PARTNER_2_3_700_1050.png",
      "Landscape_Image": "https://images.fancode.com/aig/match/v1/137182_CASACARDS_PARTNER_7_2_1920_548.png",
      "provider": "FanCode",
      "language": [
        "English"
      ],
      "isLive": true,
      "metaDetailVerbiage": "English • Cricket • 18+",
      "genre": "Cricket"
    },
    {
      "id": "137485",
      "name": "Abu Dhabi VS Dubai",
      "tounament": "Emirates D20 Tournament, 2025",
      "Portrait_Image": "https://images.fancode.com/aig/match/v1/137485_CASACARDS_PARTNER_2_3_700_1050.png",
      "Landscape_Image": "https://images.fancode.com/aig/match/v1/137485_CASACARDS_PARTNER_16_9_1920_1080.png",
      "provider": "FanCode",
      "language": [
        "English"
      ],
      "isLive": true,
      "metaDetailVerbiage": "English • Cricket • U",
      "genre": "Cricket"
    },
    {
      "id": "136860",
      "name": "Acciona Spanish Open presented by Madrid",
      "tounament": "Acciona Spanish Open presented by Madrid",
      "Portrait_Image": "https://images.fancode.com/aig/match/v1/136860_CASACARDS_PARTNER_2_3_700_1050.png",
      "Landscape_Image": "https://images.fancode.com/aig/match/v1/136860_CASACARDS_PARTNER_16_9_1920_1080.png",
      "provider": "FanCode",
      "language": [
        "English"
      ],
      "isLive": true,
      "metaDetailVerbiage": "English • Golf • U",
      "genre": "Golf"
    },
    {
      "id": "1540055306",
      "name": "BWF Arctic Open: QFs",
      "tounament": "Watch the live stream of the Quarter-finals from BWF Arctic Open 2025",
      "Portrait_Image": "https://img.hotstar.com/image/upload/f_auto/sources/r1/cms/prod/9904/1760071119904-h",
      "Landscape_Image": "https://img.hotstar.com/image/upload/f_auto,t_hcdl/sources/r1/cms/prod/9904/1760071119904-h",
      "provider": "Hotstar",
      "language": [
        "English"
      ],
      "isLive": true,
      "metaDetailVerbiage": "English • Sports",
      "genre": "Sports"
    }
  ]
}
