{
  "success": true,
  "message": "Live matches fetched successfully",
  "total": 4,
  "updatedAt": "3/11/2025, 2:28:38 pm",
  "data": [
    {
      "content_id": "1540056068",
      "title": "Celebrating Champions",
      "description": "Follow India Women's trophy celebrations after their win in the ICC Women's Cricket World Cup 2025 final",
      "image": "https://img.hotstar.com/image/upload/f_auto,q_90,w_720/sources/r1/cms/prod/7048/1762118937048-h",
      "poster": "https://img.hotstar.com/image/upload/f_auto,q_90,w_720/sources/r1/cms/prod/1983/1762095871983-i",
      "languages": {
        "English": "eng",
        "Hindi": "hin"
      },
      "tags": [
        "U",
        "2 Languages",
        "Cricket"
      ],
      "watch_url": "https://www.hotstar.com/in/shows/celebrating-champions/1540056068/live/watch",
      "status": "LIVE",
      "isLive": true
    },
    {
      "content_id": "1540055072",
      "title": "Tamil Nadu vs Vidarbha: Day 3",
      "description": "Watch the live stream of Day 3 from the IDFC FIRST Bank Ranji Trophy 2025/26 match between Tamil Nadu and Vidarbha",
      "image": "https://img.hotstar.com/image/upload/f_auto,q_90,w_720/sources/r1/cms/prod/2976/1762082252976-h",
      "poster": "https://img.hotstar.com/image/upload/f_auto,q_90,w_720/sources/r1/cms/prod/2734/1762082212734-i",
      "languages": {
        "English": "eng"
      },
      "tags": [
        "English",
        "Cricket"
      ],
      "watch_url": "https://www.hotstar.com/in/sports/cricket/tamil-nadu-vs-vidarbha-day-3/1540055072/video/live/watch",
      "status": "LIVE",
      "isLive": true
    },
    {
      "content_id": "1540055078",
      "title": "Himachal Pradesh vs Hyderabad: Day 3",
      "description": "Watch the live stream of Day 3 from the IDFC FIRST Bank Ranji Trophy 2025/26 match between Himachal Pradesh and Hyderabad",
      "image": "https://img.hotstar.com/image/upload/f_auto,q_90,w_720/sources/r1/cms/prod/9101/1762081869101-h",
      "poster": "https://img.hotstar.com/image/upload/f_auto,q_90,w_720/sources/r1/cms/prod/5438/1762081885438-i",
      "languages": {
        "English": "eng"
      },
      "tags": [
        "English",
        "Cricket"
      ],
      "watch_url": "https://www.hotstar.com/in/sports/cricket/himachal-pradesh-vs-hyderabad-day-3/1540055078/video/live/watch",
      "status": "LIVE",
      "isLive": true
    },
    {
      "content_id": "1540055075",
      "title": "Punjab vs Goa: Day 3",
      "description": "Watch the live stream of Day 3 from the IDFC FIRST Bank Ranji Trophy 2025/26 match between Punjab and Goa",
      "image": "https://img.hotstar.com/image/upload/f_auto,q_90,w_720/sources/r1/cms/prod/5289/1762081285289-h",
      "poster": "https://img.hotstar.com/image/upload/f_auto,q_90,w_720/sources/r1/cms/prod/8101/1762081328101-i",
      "languages": {
        "English": "eng"
      },
      "tags": [
        "English",
        "Cricket"
      ],
      "watch_url": "https://www.hotstar.com/in/sports/cricket/punjab-vs-goa-day-3/1540055075/video/live/watch",
      "status": "LIVE",
      "isLive": true
    }
  ]
}
