{
  "success": true,
  "message": "Live matches fetched successfully",
  "total": 16,
  "updatedAt": "18/12/2025, 01:28:17 AM",
  "data": [
    {
      "id": 1,
      "isLive": true,
      "contentId": "138905",
      "name": "CFT vs RM",
      "genre": "football",
      "language": "english",
      "provider": "FanCode",
      "content_type": "sport",
      "image": [
        "https://images.ottplay.com/backdrops/c8e88ce7a384ee58037c6429961845b0.jpg"
      ],
      "posters": [
        "https://images.ottplay.com/posters/9493f86ca114cf4e0c2b522cc5445618.jpg"
      ],
      "providerInfo": {
        "id": "63ce216c483822001ca300a4",
        "name": "FanCode",
        "hashId": "c60fe425e3269"
      }
    },
    {
      "id": 2,
      "isLive": true,
      "contentId": "137609",
      "name": "ROM-W vs POL-W",
      "genre": "football",
      "language": "english",
      "provider": "FanCode",
      "content_type": "sport",
      "image": [
        "https://images.ottplay.com/backdrops/346ef7d0b4948437a95aa3fdb812d8db.jpg"
      ],
      "posters": [
        "https://images.ottplay.com/posters/d7b95116f1d66abe73e366fc24b04071.jpg"
      ],
      "providerInfo": {
        "id": "63ce216c483822001ca300a4",
        "name": "FanCode",
        "hashId": "c60fe425e3269"
      }
    },
    {
      "id": 3,
      "isLive": true,
      "contentId": "137601",
      "name": "WOL-W vs CHE-W",
      "genre": "football",
      "language": "english",
      "provider": "FanCode",
      "content_type": "sport",
      "image": [
        "https://images.ottplay.com/backdrops/787851923269ae9a2fd0e3ea9a611ec5.jpg"
      ],
      "posters": [
        "https://images.ottplay.com/posters/d3783f1070a8fac4e046326c144eac07.jpg"
      ],
      "providerInfo": {
        "id": "63ce216c483822001ca300a4",
        "name": "FanCode",
        "hashId": "c60fe425e3269"
      }
    },
    {
      "id": 4,
      "isLive": true,
      "contentId": "137606",
      "name": "PFC-W vs BAR-W",
      "genre": "football",
      "language": "english",
      "provider": "FanCode",
      "content_type": "sport",
      "image": [
        "https://images.ottplay.com/backdrops/ad4542fb46e81a382cf28c3237d7b115.jpg"
      ],
      "posters": [
        "https://images.ottplay.com/posters/4a52d688c28414c78c6c47ad5b6a4175.jpg"
      ],
      "providerInfo": {
        "id": "63ce216c483822001ca300a4",
        "name": "FanCode",
        "hashId": "c60fe425e3269"
      }
    },
    {
      "id": 5,
      "isLive": true,
      "contentId": "138904",
      "name": "ALA vs SEV",
      "genre": "football",
      "language": "english",
      "provider": "FanCode",
      "content_type": "sport",
      "image": [
        "https://images.ottplay.com/backdrops/0df85115f2796be9734c2517fff490e7.jpg",
        "https://images.ottplay.com/backdrops/25143c75868f46a8a8597171d9c9d34c.jpg"
      ],
      "posters": [
        "https://images.ottplay.com/posters/d33616bbc8b4bc35ccc988b90fc41eb4.jpg",
        "https://images.ottplay.com/posters/adf7496789fb27281f9558be1570945c.jpg"
      ],
      "providerInfo": {
        "id": "63ce216c483822001ca300a4",
        "name": "FanCode",
        "hashId": "c60fe425e3269"
      }
    },
    {
      "id": 6,
      "isLive": true,
      "contentId": "137602",
      "name": "TWE-W vs RM-W",
      "genre": "football",
      "language": "english",
      "provider": "FanCode",
      "content_type": "sport",
      "image": [
        "https://images.ottplay.com/backdrops/09741ca132478e3e17d89b1f18cbc170.jpg"
      ],
      "posters": [
        "https://images.ottplay.com/posters/4ca817e29c983a2abe301f1c8f6cc817.jpg"
      ],
      "providerInfo": {
        "id": "63ce216c483822001ca300a4",
        "name": "FanCode",
        "hashId": "c60fe425e3269"
      }
    },
    {
      "id": 7,
      "isLive": true,
      "contentId": "137603",
      "name": "BEN-W vs PFC-W",
      "genre": "football",
      "language": "english",
      "provider": "FanCode",
      "content_type": "sport",
      "image": [
        "https://images.ottplay.com/backdrops/e197ac6f3e996a97881ded9e26222e77.jpg"
      ],
      "posters": [
        "https://images.ottplay.com/posters/76afdbd0a0fd4fd6454a25a35e23e0de.jpg"
      ],
      "providerInfo": {
        "id": "63ce216c483822001ca300a4",
        "name": "FanCode",
        "hashId": "c60fe425e3269"
      }
    },
    {
      "id": 8,
      "isLive": true,
      "contentId": "137604",
      "name": "OLY-W vs ATL-W",
      "genre": "football",
      "language": "english",
      "provider": "FanCode",
      "content_type": "sport",
      "image": [
        "https://images.ottplay.com/backdrops/8371e8624e7ef1e563ca55caecd94c90.jpg"
      ],
      "posters": [
        "https://images.ottplay.com/posters/d8499226ac97bee260f07c513c4560da.jpg"
      ],
      "providerInfo": {
        "id": "63ce216c483822001ca300a4",
        "name": "FanCode",
        "hashId": "c60fe425e3269"
      }
    },
    {
      "id": 9,
      "isLive": true,
      "contentId": "137605",
      "name": "JUV-W vs MUN-W",
      "genre": "football",
      "language": "english",
      "provider": "FanCode",
      "content_type": "sport",
      "image": [
        "https://images.ottplay.com/backdrops/abde5aceb7015833ec8e18c11bc356e2.jpg"
      ],
      "posters": [
        "https://images.ottplay.com/posters/46d23fef7aee1d23c6df452896bac37a.jpg"
      ],
      "providerInfo": {
        "id": "63ce216c483822001ca300a4",
        "name": "FanCode",
        "hashId": "c60fe425e3269"
      }
    },
    {
      "id": 10,
      "isLive": true,
      "contentId": "137607",
      "name": "OHL-W vs ARS-W",
      "genre": "football",
      "language": "english",
      "provider": "FanCode",
      "content_type": "sport",
      "image": [
        "https://images.ottplay.com/backdrops/bcc354ce65edb16c99220307524f24c1.jpg"
      ],
      "posters": [
        "https://images.ottplay.com/posters/8cd3181b073c4fa47bce4844a971ab5f.jpg"
      ],
      "providerInfo": {
        "id": "63ce216c483822001ca300a4",
        "name": "FanCode",
        "hashId": "c60fe425e3269"
      }
    },
    {
      "id": 11,
      "isLive": true,
      "contentId": "137608",
      "name": "BAY-W vs VAL-W",
      "genre": "football",
      "language": "english",
      "provider": "FanCode",
      "content_type": "sport",
      "image": [
        "https://images.ottplay.com/backdrops/fe8627ebd3e888f055f495a4db5c4d33.jpg"
      ],
      "posters": [
        "https://images.ottplay.com/posters/64cab443f5bee98e3e58cb2740d71ca8.jpg"
      ],
      "providerInfo": {
        "id": "63ce216c483822001ca300a4",
        "name": "FanCode",
        "hashId": "c60fe425e3269"
      }
    },
    {
      "id": 12,
      "isLive": true,
      "contentId": "137983",
      "name": "MCI vs BRE",
      "genre": "football",
      "language": "english",
      "provider": "FanCode",
      "content_type": "sport",
      "image": [
        "https://images.ottplay.com/backdrops/61bb9092da478c1819929c867d4796bd.jpg"
      ],
      "posters": [
        "https://images.ottplay.com/posters/8151da70704e144318da493394b48158.jpg"
      ],
      "providerInfo": {
        "id": "63ce216c483822001ca300a4",
        "name": "FanCode",
        "hashId": "c60fe425e3269"
      }
    },
    {
      "id": 13,
      "isLive": true,
      "contentId": "138900",
      "name": "ABA vs ATL",
      "genre": "football",
      "language": "english",
      "provider": "FanCode",
      "content_type": "sport",
      "image": [
        "https://images.ottplay.com/backdrops/f65310c0783ad5dab03140b6fdc748ad.jpg"
      ],
      "posters": [
        "https://images.ottplay.com/posters/0e62d2a0688055d20bc3dbba0dad8553.jpg"
      ],
      "providerInfo": {
        "id": "63ce216c483822001ca300a4",
        "name": "FanCode",
        "hashId": "c60fe425e3269"
      }
    },
    {
      "id": 14,
      "isLive": true,
      "contentId": "138901",
      "name": "ALB vs CEV",
      "genre": "football",
      "language": "english",
      "provider": "FanCode",
      "content_type": "sport",
      "image": [
        "https://images.ottplay.com/backdrops/d3a07a734f940701c560a20d7a112e7e.jpg"
      ],
      "posters": [
        "https://images.ottplay.com/posters/78d676e45a22ac71b409046c97535a7d.jpg"
      ],
      "providerInfo": {
        "id": "63ce216c483822001ca300a4",
        "name": "FanCode",
        "hashId": "c60fe425e3269"
      }
    },
    {
      "id": 15,
      "isLive": true,
      "contentId": "138902",
      "name": "HUE vs OSN",
      "genre": "football",
      "language": "english",
      "provider": "FanCode",
      "content_type": "sport",
      "image": [
        "https://images.ottplay.com/backdrops/0fe784f8e77b90b25f172c80b87e200b.jpg"
      ],
      "posters": [
        "https://images.ottplay.com/posters/14cb0ebd49d1eb3396a4d2cb0f6f9f75.jpg"
      ],
      "providerInfo": {
        "id": "63ce216c483822001ca300a4",
        "name": "FanCode",
        "hashId": "c60fe425e3269"
      }
    },
    {
      "id": 16,
      "isLive": true,
      "contentId": "138903",
      "name": "RAC vs VIL",
      "genre": "football",
      "language": "english",
      "provider": "FanCode",
      "content_type": "sport",
      "image": [
        "https://images.ottplay.com/backdrops/10c8a9ee571e654c9a3360304e9255a3.jpg"
      ],
      "posters": [
        "https://images.ottplay.com/posters/70437501cada78e96b43dab399b31ade.jpg"
      ],
      "providerInfo": {
        "id": "63ce216c483822001ca300a4",
        "name": "FanCode",
        "hashId": "c60fe425e3269"
      }
    }
  ]
}
