{
  "status": "success",
  "message": "Live matches fetched successfully",
  "total": 4,
  "updatedAt": "27/09/2025, 09:39:21 am",
  "data": [
    {
      "id": 1,
      "contentId": "137079",
      "name": "TET vs RIF",
      "genre": "cricket",
      "isLive": true,
      "content_type": "sport",
      "provider": "FanCode",
      "language": "english",
      "sports_category": "LIVE_SPORT",
      "image": [
        "https://images.ottplay.com/backdrops/5e3ded00d2244721163f2f6c16f6af1b.jpg"
      ],
      "posters": [
        "https://images.ottplay.com/posters/a86199f531371efacebdd7b1d156bce5.jpg"
      ],
      "providerInfo": {
        "id": "63ce216c483822001ca300a4",
        "name": "FanCode",
        "hashId": "c60fe425e3269"
      }
    },
    {
      "id": 3,
      "contentId": "1540051738",
      "name": "SFs: BWF Korea Open",
      "genre": "badminton",
      "isLive": true,
      "content_type": "sport",
      "provider": "JioHotstar",
      "language": "english",
      "sports_category": "LIVE_SPORT",
      "image": [
        "https://images.ottplay.com/images/075b307d1011e1f1b2b591096003dfe6.jpg"
      ],
      "posters": [
        "https://images.ottplay.com/posters/b7655dfc790da9d633cb942c3f470a60.jpg"
      ],
      "providerInfo": {
        "id": "67977987ed126c0029b9f20c",
        "name": "JioHotstar",
        "hashId": "4025a7f67d456"
      }
    },
    {
      "id": 4,
      "contentId": "137326",
      "name": "RUC vs CD",
      "genre": "pickleball",
      "isLive": true,
      "content_type": "sport",
      "provider": "FanCode",
      "language": "english",
      "sports_category": "LIVE_SPORT",
      "image": [
        "https://images.ottplay.com/backdrops/d7127d911a4974177de1d96451cc2dfe.jpg"
      ],
      "posters": [
        "https://images.ottplay.com/posters/f784282f7f283e7816609ee1b05eee69.jpg"
      ],
      "providerInfo": {
        "id": "63ce216c483822001ca300a4",
        "name": "FanCode",
        "hashId": "c60fe425e3269"
      }
    },
    {
      "id": 5,
      "contentId": "137327",
      "name": "RUC vs CDC",
      "genre": "pickleball",
      "isLive": true,
      "content_type": "sport",
      "provider": "FanCode",
      "language": "english",
      "sports_category": "LIVE_SPORT",
      "image": [
        "https://images.ottplay.com/backdrops/b7f50747d5125fd454256e6b64db04ae.jpg"
      ],
      "posters": [
        "https://images.ottplay.com/posters/a788094a89b3622001d3635154017060.jpg"
      ],
      "providerInfo": {
        "id": "63ce216c483822001ca300a4",
        "name": "FanCode",
        "hashId": "c60fe425e3269"
      }
    }
  ]
}
