{
  "success": true,
  "message": "Live matches fetched successfully",
  "total": 8,
  "updatedAt": "12/05/2026, 08:40:48 PM",
  "data": [
    {
      "id": 1,
      "isLive": true,
      "contentId": "141957",
      "name": "GUY vs WIC",
      "genre": "cricket",
      "language": "english",
      "provider": "FanCode",
      "content_type": "sport",
      "image": [
        "https://images.ottplay.com/backdrops/779e72d5c7a161ac0a78bc375f0afad6.jpg"
      ],
      "posters": [
        "https://images.ottplay.com/posters/c38f753b7ee4e069176e4336ac99c30f.jpg"
      ],
      "providerInfo": {
        "id": "63ce216c483822001ca300a4",
        "name": "FanCode",
        "hashId": "c60fe425e3269"
      }
    },
    {
      "id": 2,
      "isLive": true,
      "contentId": "140500",
      "name": "MBSG vs KSHI",
      "genre": "football",
      "language": "english",
      "provider": "FanCode",
      "content_type": "sport",
      "image": [
        "https://images.ottplay.com/backdrops/da45a31268b6eaf47b24bd1af6ae38bf.jpg"
      ],
      "posters": [
        "https://images.ottplay.com/posters/2bf0cb3df0f561c9b31b21900d1a112e.jpg"
      ],
      "providerInfo": {
        "id": "63ce216c483822001ca300a4",
        "name": "FanCode",
        "hashId": "c60fe425e3269"
      }
    },
    {
      "id": 3,
      "isLive": true,
      "contentId": "141956",
      "name": "TNT vs BAR",
      "genre": "cricket",
      "language": "english",
      "provider": "FanCode",
      "content_type": "sport",
      "image": [
        "https://images.ottplay.com/backdrops/88b26e8028ab6f2cf5734613f14fae54.jpg"
      ],
      "posters": [
        "https://images.ottplay.com/posters/d09eb772c885ea680db4c796782425ad.jpg"
      ],
      "providerInfo": {
        "id": "63ce216c483822001ca300a4",
        "name": "FanCode",
        "hashId": "c60fe425e3269"
      }
    },
    {
      "id": 4,
      "isLive": true,
      "contentId": "142641",
      "name": "ATP vs LOC",
      "genre": "lawn-tennis",
      "language": "english",
      "provider": "FanCode",
      "content_type": "sport",
      "image": [
        "https://images.ottplay.com/backdrops/dd70fa14872066bb47f6767a5a7e0900.jpg"
      ],
      "posters": [
        "https://images.ottplay.com/posters/d7c7bf997f0d0c531f8d2bb72c53c71f.jpg"
      ],
      "providerInfo": {
        "id": "63ce216c483822001ca300a4",
        "name": "FanCode",
        "hashId": "c60fe425e3269"
      }
    },
    {
      "id": 6,
      "isLive": true,
      "contentId": "1090530139",
      "name": "Namdhari Sports Club vs Gokulam Kerala FC - 12 May 2026",
      "genre": "football",
      "language": "english",
      "provider": "SonyLIV",
      "content_type": "sport",
      "image": [
        "https://images.ottplay.com/images/e77dcbe203f5b39792162f9d98d87bb1.jpg",
        "https://images.ottplay.com/images/4cc8920b739527eb22ae670f21d20a9f.jpg",
        "https://images.ottplay.com/images/7ce97aa4f9b6115071bc82b1f003328e.jpg",
        "https://images.ottplay.com/images/4342976c49bae39c6580df49253f30e4.jpg",
        "https://images.ottplay.com/images/5d17352d4c77a5affd182832bb4bfee0.jpg"
      ],
      "posters": [
        "https://images.ottplay.com/posters/c522fb21c312062b3c0ddaa5251cd205.jpg"
      ],
      "providerInfo": {
        "id": "5f456c2aff9ccd034434e6fd",
        "name": "SonyLIV",
        "hashId": "100dc02b90dfc"
      }
    },
    {
      "id": 7,
      "isLive": true,
      "contentId": "142639",
      "name": "ATP vs LOC",
      "genre": "lawn-tennis",
      "language": "english",
      "provider": "FanCode",
      "content_type": "sport",
      "image": [
        "https://images.ottplay.com/backdrops/0c7ae2005c97d6424ee6652bb3c32391.jpg"
      ],
      "posters": [
        "https://images.ottplay.com/posters/253a6adc337845a96ecef69188e82ed2.jpg"
      ],
      "providerInfo": {
        "id": "63ce216c483822001ca300a4",
        "name": "FanCode",
        "hashId": "c60fe425e3269"
      }
    },
    {
      "id": 8,
      "isLive": true,
      "contentId": "142231",
      "name": "ATP vs LOC",
      "genre": "lawn-tennis",
      "language": "english",
      "provider": "FanCode",
      "content_type": "sport",
      "image": [
        "https://images.ottplay.com/backdrops/477f843c167daec7be8f0bef36d5efb8.jpg"
      ],
      "posters": [
        "https://images.ottplay.com/posters/de8f4fc235d65ba2764381e7c51278f9.jpg"
      ],
      "providerInfo": {
        "id": "63ce216c483822001ca300a4",
        "name": "FanCode",
        "hashId": "c60fe425e3269"
      }
    },
    {
      "id": 9,
      "isLive": true,
      "contentId": "142232",
      "name": "ATP vs LOC",
      "genre": "lawn-tennis",
      "language": "english",
      "provider": "FanCode",
      "content_type": "sport",
      "image": [
        "https://images.ottplay.com/backdrops/c1c1b6b7acaab7a1a815287061907e92.jpg"
      ],
      "posters": [
        "https://images.ottplay.com/posters/fdc3317b8da71da20632445f1f727a77.jpg"
      ],
      "providerInfo": {
        "id": "63ce216c483822001ca300a4",
        "name": "FanCode",
        "hashId": "c60fe425e3269"
      }
    }
  ]
}
