{
  "success": true,
  "message": "Live matches fetched successfully",
  "total": 10,
  "updatedAt": "08/04/2026, 07:28:54 PM",
  "data": [
    {
      "id": 1,
      "isLive": true,
      "contentId": "141628",
      "name": "UZ-U20 vs JOR-U20",
      "genre": "football",
      "language": "english",
      "provider": "FanCode",
      "content_type": "sport",
      "image": [
        "https://images.ottplay.com/backdrops/1b1cfcb8e96eb7297075873c02e1308b.jpg"
      ],
      "posters": [
        "https://images.ottplay.com/posters/53505c7a1ecc54890071637a6a53d104.jpg"
      ],
      "providerInfo": {
        "id": "63ce216c483822001ca300a4",
        "name": "FanCode",
        "hashId": "c60fe425e3269"
      }
    },
    {
      "id": 2,
      "isLive": true,
      "contentId": "141627",
      "name": "DPR-U20 vs KR-U20",
      "genre": "football",
      "language": "english",
      "provider": "FanCode",
      "content_type": "sport",
      "image": [
        "https://images.ottplay.com/backdrops/2efbac6c294bbc574eb4a71f66d89d7f.jpg"
      ],
      "posters": [
        "https://images.ottplay.com/posters/a00f08f9f7786e8cf7b9523c12f7a4a5.jpg"
      ],
      "providerInfo": {
        "id": "63ce216c483822001ca300a4",
        "name": "FanCode",
        "hashId": "c60fe425e3269"
      }
    },
    {
      "id": 3,
      "isLive": true,
      "contentId": "1540065721",
      "name": "DC vs GT",
      "genre": "cricket",
      "language": "english",
      "provider": "JioHotstar",
      "content_type": "sport",
      "image": [
        "https://images.ottplay.com/images/565d731a45af519db463f06551b4192d.jpg"
      ],
      "posters": [
        "https://images.ottplay.com/posters/f47b1af15a1fd7c74e1d24b969839491.jpg"
      ],
      "providerInfo": {
        "id": "67977987ed126c0029b9f20c",
        "name": "JioHotstar",
        "hashId": "4025a7f67d456"
      }
    },
    {
      "id": 4,
      "isLive": true,
      "contentId": "141899",
      "name": "BOT-W vs ZAM-W",
      "genre": "cricket",
      "language": "english",
      "provider": "FanCode",
      "content_type": "sport",
      "image": [
        "https://images.ottplay.com/backdrops/ed188e1ba140a52b45d04746387b376c.jpg"
      ],
      "posters": [
        "https://images.ottplay.com/posters/5ee0ec8b69ded2907cf908f50fe8d195.jpg"
      ],
      "providerInfo": {
        "id": "63ce216c483822001ca300a4",
        "name": "FanCode",
        "hashId": "c60fe425e3269"
      }
    },
    {
      "id": 5,
      "isLive": true,
      "contentId": "141898",
      "name": "LESW vs MOZW",
      "genre": "cricket",
      "language": "english",
      "provider": "FanCode",
      "content_type": "sport",
      "image": [
        "https://images.ottplay.com/backdrops/2e2242395f577a1c2d6ad7ec59f8da09.jpg"
      ],
      "posters": [
        "https://images.ottplay.com/posters/05fdf6682d0682bc70520da1e0188c5f.jpg"
      ],
      "providerInfo": {
        "id": "63ce216c483822001ca300a4",
        "name": "FanCode",
        "hashId": "c60fe425e3269"
      }
    },
    {
      "id": 6,
      "isLive": true,
      "contentId": "141668",
      "name": "ATP vs LOC",
      "genre": "lawn-tennis",
      "language": "english",
      "provider": "FanCode",
      "content_type": "sport",
      "image": [
        "https://images.ottplay.com/backdrops/7c26096d5b7be038cfa698f2f118fad2.jpg"
      ],
      "posters": [
        "https://images.ottplay.com/posters/18709a2afe16e937178a17d1cd62bbe4.jpg"
      ],
      "providerInfo": {
        "id": "63ce216c483822001ca300a4",
        "name": "FanCode",
        "hashId": "c60fe425e3269"
      }
    },
    {
      "id": 7,
      "isLive": true,
      "contentId": "141667",
      "name": "ATP vs LOC",
      "genre": "lawn-tennis",
      "language": "english",
      "provider": "FanCode",
      "content_type": "sport",
      "image": [
        "https://images.ottplay.com/backdrops/2f8ad7ffa8351e06a72a79ff13ef9765.jpg"
      ],
      "posters": [
        "https://images.ottplay.com/posters/aa8624b429a4782ecc65205ebb062074.jpg"
      ],
      "providerInfo": {
        "id": "63ce216c483822001ca300a4",
        "name": "FanCode",
        "hashId": "c60fe425e3269"
      }
    },
    {
      "id": 8,
      "isLive": true,
      "contentId": "141670",
      "name": "ATP vs LOC",
      "genre": "lawn-tennis",
      "language": "english",
      "provider": "FanCode",
      "content_type": "sport",
      "image": [
        "https://images.ottplay.com/backdrops/332f2cfae968d1ad7535d49382229468.jpg"
      ],
      "posters": [
        "https://images.ottplay.com/posters/87b8e4c6680ff688b3327849cf70c75c.jpg"
      ],
      "providerInfo": {
        "id": "63ce216c483822001ca300a4",
        "name": "FanCode",
        "hashId": "c60fe425e3269"
      }
    },
    {
      "id": 9,
      "isLive": true,
      "contentId": "141669",
      "name": "ATP vs LOC",
      "genre": "lawn-tennis",
      "language": "english",
      "provider": "FanCode",
      "content_type": "sport",
      "image": [
        "https://images.ottplay.com/backdrops/8e5bf6f5bf87bba1c5ead0e4052ab7ac.jpg"
      ],
      "posters": [
        "https://images.ottplay.com/posters/d84e10c6bb549f03579cfd941fa6aaa0.jpg"
      ],
      "providerInfo": {
        "id": "63ce216c483822001ca300a4",
        "name": "FanCode",
        "hashId": "c60fe425e3269"
      }
    },
    {
      "id": 10,
      "isLive": true,
      "contentId": "141649",
      "name": "SCO vs OMN",
      "genre": "cricket",
      "language": "english",
      "provider": "FanCode",
      "content_type": "sport",
      "image": [
        "https://images.ottplay.com/backdrops/93d98ecd86ca7c88aa527451751ed537.jpg"
      ],
      "posters": [
        "https://images.ottplay.com/posters/cfef665ce088c2c24e4e5e2ab65b2b95.jpg"
      ],
      "providerInfo": {
        "id": "63ce216c483822001ca300a4",
        "name": "FanCode",
        "hashId": "c60fe425e3269"
      }
    }
  ]
}
