{
  "success": true,
  "message": "Live matches fetched successfully",
  "total": 1,
  "updatedAt": "24/05/2026, 04:00:59 AM",
  "data": [
    {
      "id": 1,
      "isLive": true,
      "contentId": "139687",
      "name": "F1A vs LOC",
      "genre": "racing",
      "language": "english",
      "provider": "FanCode",
      "content_type": "sport",
      "image": [
        "https://images.ottplay.com/backdrops/277078b7bc5891cc65fc9edd8f42160e.jpg"
      ],
      "posters": [
        "https://images.ottplay.com/posters/ef5d4bbfac0a8ead8314cf6c7bc32ed4.jpg"
      ],
      "providerInfo": {
        "id": "63ce216c483822001ca300a4",
        "name": "FanCode",
        "hashId": "c60fe425e3269"
      }
    }
  ]
}
