{
  "success": true,
  "message": "Live matches fetched successfully",
  "total": 11,
  "updatedAt": "18/05/2026, 12:13:17 AM",
  "data": [
    {
      "id": 1,
      "isLive": true,
      "contentId": "142630",
      "name": "PGA Championship 2026",
      "genre": "golf",
      "language": "english",
      "provider": "FanCode",
      "content_type": "sport",
      "image": [
        "https://images.ottplay.com/backdrops/fee4699ad187cfa48d24a622ff347e0e.jpg"
      ],
      "posters": [
        "https://images.ottplay.com/posters/08cb55c9e9b45878913262f17bcb249d.jpg"
      ],
      "providerInfo": {
        "id": "63ce216c483822001ca300a4",
        "name": "FanCode",
        "hashId": "c60fe425e3269"
      }
    },
    {
      "id": 2,
      "isLive": true,
      "contentId": "131190",
      "name": "ATH vs CEV",
      "genre": "football",
      "language": "english",
      "provider": "FanCode",
      "content_type": "sport",
      "image": [
        "https://images.ottplay.com/backdrops/a10ee793f72aae857afb724f890194b2.jpg"
      ],
      "posters": [
        "https://images.ottplay.com/posters/f54e3ee303f6c242cd6ba26bf2aa8e73.jpg"
      ],
      "providerInfo": {
        "id": "63ce216c483822001ca300a4",
        "name": "FanCode",
        "hashId": "c60fe425e3269"
      }
    },
    {
      "id": 3,
      "isLive": true,
      "contentId": "131191",
      "name": "ATL vs GIR",
      "genre": "football",
      "language": "english",
      "provider": "FanCode",
      "content_type": "sport",
      "image": [
        "https://images.ottplay.com/backdrops/63f505b6b0b6b1bd65b45a1bbe0e4d08.jpg"
      ],
      "posters": [
        "https://images.ottplay.com/posters/ab15a90c4c8d8001429997ee262d5e10.jpg"
      ],
      "providerInfo": {
        "id": "63ce216c483822001ca300a4",
        "name": "FanCode",
        "hashId": "c60fe425e3269"
      }
    },
    {
      "id": 4,
      "isLive": true,
      "contentId": "131193",
      "name": "ELC vs GEF",
      "genre": "football",
      "language": "english",
      "provider": "FanCode",
      "content_type": "sport",
      "image": [
        "https://images.ottplay.com/backdrops/834e7d3935fcc534a583dbdf5b0a5286.jpg"
      ],
      "posters": [
        "https://images.ottplay.com/posters/7e5e2f58f04ab033a27906bc3b715b96.jpg"
      ],
      "providerInfo": {
        "id": "63ce216c483822001ca300a4",
        "name": "FanCode",
        "hashId": "c60fe425e3269"
      }
    },
    {
      "id": 5,
      "isLive": true,
      "contentId": "131194",
      "name": "LE vs MRC",
      "genre": "football",
      "language": "english",
      "provider": "FanCode",
      "content_type": "sport",
      "image": [
        "https://images.ottplay.com/backdrops/048cc27d17775e2ca06d90e181300a05.jpg"
      ],
      "posters": [
        "https://images.ottplay.com/posters/6b985e86ec29bfbb662980837ed925fe.jpg"
      ],
      "providerInfo": {
        "id": "63ce216c483822001ca300a4",
        "name": "FanCode",
        "hashId": "c60fe425e3269"
      }
    },
    {
      "id": 6,
      "isLive": true,
      "contentId": "131195",
      "name": "RVL vs VIL",
      "genre": "football",
      "language": "english",
      "provider": "FanCode",
      "content_type": "sport",
      "image": [
        "https://images.ottplay.com/backdrops/24302447426c1c4bc16228efa1bad73e.jpg"
      ],
      "posters": [
        "https://images.ottplay.com/posters/e54fdba6b6a00634bf0a7be6b3fe64f9.jpg"
      ],
      "providerInfo": {
        "id": "63ce216c483822001ca300a4",
        "name": "FanCode",
        "hashId": "c60fe425e3269"
      }
    },
    {
      "id": 7,
      "isLive": true,
      "contentId": "131196",
      "name": "RS vs VAL",
      "genre": "football",
      "language": "english",
      "provider": "FanCode",
      "content_type": "sport",
      "image": [
        "https://images.ottplay.com/backdrops/7b1354d41645d554f93074079826a539.jpg"
      ],
      "posters": [
        "https://images.ottplay.com/posters/3efa886bda8442fa2a0552763c3f0058.jpg"
      ],
      "providerInfo": {
        "id": "63ce216c483822001ca300a4",
        "name": "FanCode",
        "hashId": "c60fe425e3269"
      }
    },
    {
      "id": 8,
      "isLive": true,
      "contentId": "131197",
      "name": "RO vs ALA",
      "genre": "football",
      "language": "english",
      "provider": "FanCode",
      "content_type": "sport",
      "image": [
        "https://images.ottplay.com/backdrops/dc068b9e65b9651a52029bd66d682a10.jpg"
      ],
      "posters": [
        "https://images.ottplay.com/posters/c4f63129a50e3f3ae72c2de7f0d67f31.jpg"
      ],
      "providerInfo": {
        "id": "63ce216c483822001ca300a4",
        "name": "FanCode",
        "hashId": "c60fe425e3269"
      }
    },
    {
      "id": 9,
      "isLive": true,
      "contentId": "131198",
      "name": "OSN vs ESL",
      "genre": "football",
      "language": "english",
      "provider": "FanCode",
      "content_type": "sport",
      "image": [
        "https://images.ottplay.com/backdrops/af0c824b82e9bec0e46b1f123113c575.jpg"
      ],
      "posters": [
        "https://images.ottplay.com/posters/7188723f53ece96a0ee3e912eacf00bb.jpg"
      ],
      "providerInfo": {
        "id": "63ce216c483822001ca300a4",
        "name": "FanCode",
        "hashId": "c60fe425e3269"
      }
    },
    {
      "id": 10,
      "isLive": true,
      "contentId": "131199",
      "name": "SEV vs RM",
      "genre": "football",
      "language": "english",
      "provider": "FanCode",
      "content_type": "sport",
      "image": [
        "https://images.ottplay.com/backdrops/a70cb3dd30829eba8f73980d7b2bd078.jpg"
      ],
      "posters": [
        "https://images.ottplay.com/posters/c96742e3a622a26de6c3341d0810aa14.jpg"
      ],
      "providerInfo": {
        "id": "63ce216c483822001ca300a4",
        "name": "FanCode",
        "hashId": "c60fe425e3269"
      }
    },
    {
      "id": 12,
      "isLive": true,
      "contentId": "141958",
      "name": "GUY vs TNT",
      "genre": "cricket",
      "language": "english",
      "provider": "FanCode",
      "content_type": "sport",
      "image": [
        "https://images.ottplay.com/backdrops/cricket.jpg",
        "https://images.ottplay.com/backdrops/1df8e5ff58b819065ac526049294377c.jpg"
      ],
      "posters": [
        "https://images.ottplay.com/posters/d5449f26ba6fe1dd04defd6b4e8544cd.jpg"
      ],
      "providerInfo": {
        "id": "63ce216c483822001ca300a4",
        "name": "FanCode",
        "hashId": "c60fe425e3269"
      }
    }
  ]
}
