{
  "success": true,
  "message": "Live matches fetched successfully",
  "total": 1,
  "updatedAt": "04/01/2026, 04:20:58 AM",
  "data": [
    {
      "id": 1,
      "isLive": true,
      "contentId": "1540056721",
      "name": "5th Test: Australia vs England, Day 1",
      "genre": "cricket",
      "language": "english",
      "provider": "JioHotstar",
      "content_type": "sport",
      "image": [
        "https://images.ottplay.com/images/ed3f204dfe8dd9c2a1d52b94d83ce568.jpg"
      ],
      "posters": [
        "https://images.ottplay.com/posters/617748c00a6bd2a956fff2cec6247e99.jpg"
      ],
      "providerInfo": {
        "id": "67977987ed126c0029b9f20c",
        "name": "JioHotstar",
        "hashId": "4025a7f67d456"
      }
    }
  ]
}
