{
  "success": true,
  "message": "Live matches fetched successfully",
  "total": 17,
  "updatedAt": "12/04/2026, 08:32:14 PM",
  "data": [
    {
      "id": 1,
      "isLive": true,
      "contentId": "1090526867",
      "name": "Sony Sports Ten 2",
      "genre": "Football",
      "provider": "Sony Liv",
      "image": "https://d229kpbsb5jevy.cloudfront.net/sony4/videoasset_images/manage_file/1000016905/1774593762607658_BLIGA_26_MD29_VfB-Stuttgart-vs-Hamburger_landscape_thumb.jpg"
    },
    {
      "id": 2,
      "isLive": true,
      "contentId": "1540067931",
      "name": "Chelsea vs Manchester City",
      "genre": "Football",
      "provider": "JioHotstar",
      "image": "https://img1.hotstarext.com/image/upload/f_auto/sources/r1/cms/prod/7334/1775910267334-h"
    },
    {
      "id": 3,
      "isLive": true,
      "contentId": "1090526866",
      "name": "Sony Sports Ten 2",
      "genre": "Football",
      "provider": "Sony Liv",
      "image": "https://d229kpbsb5jevy.cloudfront.net/sony4/videoasset_images/manage_file/1000016905/1774593170855658_BLIGA_26_MD29_Koln-vs-Werder_landscape_thumb.jpg"
    },
    {
      "id": 4,
      "isLive": true,
      "contentId": "1540065739",
      "name": "MI vs RCB",
      "genre": "Cricket",
      "provider": "JioHotstar",
      "image": "https://img1.hotstarext.com/image/upload/f_auto/sources/r1/cms/prod/4026/1775999754026-h"
    },
    {
      "id": 5,
      "isLive": true,
      "contentId": "1540067910",
      "name": "Crystal Palace vs Newcastle United",
      "genre": "Football",
      "provider": "JioHotstar",
      "image": "https://img1.hotstarext.com/image/upload/f_auto/sources/r1/cms/prod/7084/1775909777084-h"
    },
    {
      "id": 6,
      "isLive": true,
      "contentId": "1540067913",
      "name": "Nottingham Forest vs Aston Villa",
      "genre": "Football",
      "provider": "JioHotstar",
      "image": "https://img1.hotstarext.com/image/upload/f_auto/sources/r1/cms/prod/5427/1775909995427-h"
    },
    {
      "id": 7,
      "isLive": true,
      "contentId": "1090526841",
      "name": "Sony Sports Ten 2",
      "genre": "Football",
      "provider": "Sony Liv",
      "image": "https://d229kpbsb5jevy.cloudfront.net/sony4/videoasset_images/manage_file/1000016586/1774442624162617_IFC_Sreenidi_Deccan_FC_vs_Rajasthan_United_FC_landscape_thumb.jpg"
    },
    {
      "id": 8,
      "isLive": true,
      "contentId": "1540067928",
      "name": "Sunderland vs Tottenham Hotspur",
      "genre": "Football",
      "provider": "JioHotstar",
      "image": "https://img1.hotstarext.com/image/upload/f_auto/sources/r1/cms/prod/4772/1775909144772-h"
    },
    {
      "id": 9,
      "isLive": true,
      "contentId": "1540067988",
      "name": "MXGP Sardegna 2026",
      "genre": "Motorsports",
      "provider": "JioHotstar",
      "image": "https://img1.hotstarext.com/image/upload/f_auto/sources/r1/cms/prod/9538/1775936189538-h"
    },
    {
      "id": 10,
      "isLive": true,
      "contentId": "141949",
      "name": "Windward Islands Volcanoes VS Guyana Harpy Eagles",
      "genre": "Sports",
      "provider": "FanCode",
      "image": "https://images.fancode.com/aig/match/v1775563202327/141949_CASACARDS_PARTNER_16_9_1920_1080.png"
    },
    {
      "id": 11,
      "isLive": true,
      "contentId": "141947",
      "name": "Leeward Islands Hurricanes VS Trinidad & Tobago Red Force",
      "genre": "Sports",
      "provider": "FanCode",
      "image": "https://images.fancode.com/aig/match/v1775563202280/141947_CASACARDS_PARTNER_16_9_1920_1080.png"
    },
    {
      "id": 12,
      "isLive": true,
      "contentId": "141922",
      "name": "ATP Masters Rolex Monte-Carlo 2026",
      "genre": "Sports",
      "provider": "FanCode",
      "image": "https://images.fancode.com/aig/match/v1775383204443/141922_CASACARDS_PARTNER_16_9_1920_1080.png"
    },
    {
      "id": 13,
      "isLive": true,
      "contentId": "141688",
      "name": "Huesca VS Deportivo La Coruna",
      "genre": "Sports",
      "provider": "FanCode",
      "image": "https://images.fancode.com/aig/match/v1774680543090/141688_CASACARDS_PARTNER_16_9_1920_1080.png"
    },
    {
      "id": 14,
      "isLive": true,
      "contentId": "141632",
      "name": "Thailand U20 VS Korea Republic U20",
      "genre": "Sports",
      "provider": "FanCode",
      "image": "https://images.fancode.com/aig/match/v1775822401317/141632_CASACARDS_PARTNER_16_9_1920_1080.png"
    },
    {
      "id": 15,
      "isLive": true,
      "contentId": "140877",
      "name": "Luton Town VS Stockport County",
      "genre": "Sports",
      "provider": "FanCode",
      "image": "https://images.fancode.com/aig/match/v1775404801628/140877_CASACARDS_PARTNER_16_9_1920_1080.png"
    },
    {
      "id": 16,
      "isLive": true,
      "contentId": "140485",
      "name": "Mohun Bagan Super Giant VS Punjab FC",
      "genre": "Sports",
      "provider": "FanCode",
      "image": "https://images.fancode.com/aig/match/v1770388922703/140485_CASACARDS_PARTNER_16_9_1920_1080.png"
    },
    {
      "id": 17,
      "isLive": true,
      "contentId": "131136",
      "name": "RCD Mallorca VS Rayo Vallecano",
      "genre": "Sports",
      "provider": "FanCode",
      "image": "https://images.fancode.com/aig/match/v1/131136_CASACARDS_PARTNER_16_9_1920_1080.png"
    }
  ]
}
