{
  "success": true,
  "message": "Live matches fetched successfully",
  "total": 9,
  "updatedAt": "16/01/2026, 04:13:35 PM",
  "data": [
    {
      "id": 1,
      "isLive": true,
      "contentId": "1540060732",
      "name": "Punjab De Sher vs Karnataka Bulldozers",
      "genre": "Cricket",
      "provider": "JioHotstar",
      "image": "https://img1.hotstarext.com/image/upload/f_auto/sources/r1/cms/prod/5640/1768540675640-h"
    },
    {
      "id": 2,
      "isLive": true,
      "contentId": "1540060269",
      "name": "Sydney Sixers vs Sydney Thunder",
      "genre": "Cricket",
      "provider": "JioHotstar",
      "image": "https://img1.hotstarext.com/image/upload/f_auto/sources/r1/cms/prod/6056/1768556296056-h"
    },
    {
      "id": 3,
      "isLive": true,
      "contentId": "1540060301",
      "name": "SF: Saurashtra vs Punjab",
      "genre": "Cricket",
      "provider": "JioHotstar",
      "image": "https://img1.hotstarext.com/image/upload/f_auto/sources/r1/cms/prod/6802/1768483516802-h"
    },
    {
      "id": 4,
      "isLive": true,
      "contentId": "1540060920",
      "name": "Australia vs Ireland",
      "genre": "Cricket",
      "provider": "JioHotstar",
      "image": "https://img1.hotstarext.com/image/upload/f_auto/sources/r1/cms/prod/1001/1768491891001-h"
    },
    {
      "id": 5,
      "isLive": true,
      "contentId": "1540060923",
      "name": "Afghanistan vs South Africa",
      "genre": "Cricket",
      "provider": "JioHotstar",
      "image": "https://img1.hotstarext.com/image/upload/f_auto/sources/r1/cms/prod/225/1768492160225-h"
    },
    {
      "id": 6,
      "isLive": true,
      "contentId": "1540060557",
      "name": "Pakistan vs England",
      "genre": "Cricket",
      "provider": "JioHotstar",
      "image": "https://img1.hotstarext.com/image/upload/f_auto/sources/r1/cms/prod/4035/1768508284035-h"
    },
    {
      "id": 7,
      "isLive": true,
      "contentId": "1090499622",
      "name": "Sony Sports Ten 5",
      "genre": "Tennis",
      "provider": "Sony Liv",
      "image": "https://d229kpbsb5jevy.cloudfront.net/sony4/videoasset_images/manage_file/1000013423/176846861552253_AO26_Redbull_Baseline_live_landscape_thumb.jpg"
    },
    {
      "id": 8,
      "isLive": true,
      "contentId": "139424",
      "name": "Melbourne City VS Auckland",
      "genre": "Sports",
      "provider": "FanCode",
      "image": "https://images.fancode.com/aig/match/v1/139424_CASACARDS_PARTNER_16_9_1920_1080.png"
    },
    {
      "id": 9,
      "isLive": true,
      "contentId": "138934",
      "name": "Chattogram Royals VS Noakhali Express",
      "genre": "Sports",
      "provider": "FanCode",
      "image": "https://images.fancode.com/aig/match/v1/138934_CASACARDS_PARTNER_16_9_1920_1080.png"
    }
  ]
}
