{
  "success": true,
  "message": "Live matches fetched successfully",
  "total": 11,
  "updatedAt": "17/06/2026, 02:21:45 PM",
  "data": [
    {
      "id": 1,
      "isLive": true,
      "contentId": "1540071584",
      "name": "Jamshedpur Steelers vs Santhal Strikers",
      "genre": "Cricket",
      "provider": "JioHotstar",
      "image": "https://img1.hotstarext.com/image/upload/f_auto/sources/r1/cms/prod/4234/1781615994234-h"
    },
    {
      "id": 2,
      "isLive": true,
      "contentId": "1540071511",
      "name": "India vs Afghanistan: 2nd ODI",
      "genre": "Cricket",
      "provider": "JioHotstar",
      "image": "https://img1.hotstarext.com/image/upload/f_auto/sources/r1/cms/prod/9900/1781613829900-h"
    },
    {
      "id": 3,
      "isLive": true,
      "contentId": "1540071229",
      "name": "Novus Royals Purulia vs Sobisco Smashers Malda",
      "genre": "Cricket",
      "provider": "JioHotstar",
      "image": "https://img1.hotstarext.com/image/upload/f_auto/sources/r1/cms/prod/3630/1781615463630-h"
    },
    {
      "id": 4,
      "isLive": true,
      "contentId": "1090534875",
      "name": "Sony Sports Ten 1",
      "genre": "Cricket",
      "provider": "Sony Liv",
      "image": "https://d229kpbsb5jevy.cloudfront.net/sony4/videoasset_images/manage_file/1000019494/1781082943073523_Tri_Series26_IND_A_vs_AFG_A_landscape_thumb.jpg"
    },
    {
      "id": 5,
      "isLive": true,
      "contentId": "1090534880",
      "name": "Sony Sports Ten 1",
      "genre": "Cricket",
      "provider": "Sony Liv",
      "image": "https://d229kpbsb5jevy.cloudfront.net/sony4/videoasset_images/manage_file/1000019494/1781083041217523_Tri_Series26_IND_A_vs_AFG_A_landscape_thumb_kannada.jpg"
    },
    {
      "id": 6,
      "isLive": true,
      "contentId": "1090534879",
      "name": "Sony Sports Ten 1",
      "genre": "Cricket",
      "provider": "Sony Liv",
      "image": "https://d229kpbsb5jevy.cloudfront.net/sony4/videoasset_images/manage_file/1000019494/1781082971125523_Tri_Series26_IND_A_vs_AFG_A_landscape_thumb_hindi.jpg"
    },
    {
      "id": 7,
      "isLive": true,
      "contentId": "1090534877",
      "name": "Sony Sports Ten 1",
      "genre": "Cricket",
      "provider": "Sony Liv",
      "image": "https://d229kpbsb5jevy.cloudfront.net/sony4/videoasset_images/manage_file/1000019494/1781082981446523_Tri_Series26_IND_A_vs_AFG_A_landscape_thumb_tamil.jpg"
    },
    {
      "id": 8,
      "isLive": true,
      "contentId": "1090534878",
      "name": "Sony Sports Ten 1",
      "genre": "Cricket",
      "provider": "Sony Liv",
      "image": "https://d229kpbsb5jevy.cloudfront.net/sony4/videoasset_images/manage_file/1000019494/1781082992019523_Tri_Series26_IND_A_vs_AFG_A_landscape_thumb_telugu.jpg"
    },
    {
      "id": 9,
      "isLive": true,
      "contentId": "143181",
      "name": "Malmo Mavericks VS Vasteras United",
      "genre": "Sports",
      "provider": "FanCode",
      "image": "https://images.fancode.com/aig/match/v1781078400968/143181_CASACARDS_PARTNER_16_9_1920_1080.png"
    },
    {
      "id": 10,
      "isLive": true,
      "contentId": "143037",
      "name": "Firozpur Falcons VS Moga Mongoose",
      "genre": "Sports",
      "provider": "FanCode",
      "image": "https://images.fancode.com/aig/match/v1781085600927/143037_CASACARDS_PARTNER_16_9_1920_1080.png"
    },
    {
      "id": 11,
      "isLive": true,
      "contentId": "142968",
      "name": "Bangladesh VS Australia",
      "genre": "Sports",
      "provider": "FanCode",
      "image": "https://images.fancode.com/aig/match/v1781085600560/142968_CASACARDS_PARTNER_16_9_1920_1080.png"
    }
  ]
}
